bluefang/__init__.py
bluefang/agents.py
bluefang/commands.py
bluefang/connection.py
bluefang/constants.py
bluefang/l2cap.py
bluefang/profile.py
bluefang/servicerecords.py
bluefang-0.1.10.dist-info/DESCRIPTION.rst
bluefang-0.1.10.dist-info/METADATA
bluefang-0.1.10.dist-info/RECORD
bluefang-0.1.10.dist-info/WHEEL
bluefang-0.1.10.dist-info/metadata.json
bluefang-0.1.10.dist-info/pbr.json
bluefang-0.1.10.dist-info/top_level.txt
