Metadata-Version: 2.0
Name: bluefang
Version: 0.1.10
Summary: Bluetooth and HID utilities for Python 3
Home-page: https://www.github.com/tmcneal/bluefang
Author: Todd McNeal
Author-email: todd.mcneal@gmail.com
License: UNKNOWN
Keywords: bluetooth,hid,l2cap,bluez,pybluez,dbus
Platform: UNKNOWN
Requires-Python: >=3.4
Requires-Dist: PyBluez (==0.22)
Requires-Dist: dbus-python (==1.2.4)
